ipypetrinet/__init__.py
ipypetrinet/_frontend.py
ipypetrinet/_version.py
ipypetrinet/widget.py
ipypetrinet/labextension/build_log.json
ipypetrinet/labextension/package.json
ipypetrinet/labextension/static/lib_index_js.512882641dfd0495165a.js
ipypetrinet/labextension/static/lib_index_js.512882641dfd0495165a.js.map
ipypetrinet/labextension/static/lib_plugin_js.49f47e14fc5eca0b3a7b.js
ipypetrinet/labextension/static/lib_plugin_js.49f47e14fc5eca0b3a7b.js.map
ipypetrinet/labextension/static/lib_widget_js.a0d8d9492615002f5afb.js
ipypetrinet/labextension/static/lib_widget_js.a0d8d9492615002f5afb.js.map
ipypetrinet/labextension/static/remoteEntry.727bf604ea7a529644b3.js
ipypetrinet/labextension/static/remoteEntry.727bf604ea7a529644b3.js.map
ipypetrinet/labextension/static/style.js
ipypetrinet/labextension/static/vendors-node_modules_css-loader_dist_runtime_api_js-node_modules_dagre_index_js-node_modules_-7114b2.12878c99a99b73c91b56.js
ipypetrinet/labextension/static/vendors-node_modules_css-loader_dist_runtime_api_js-node_modules_dagre_index_js-node_modules_-7114b2.12878c99a99b73c91b56.js.map
ipypetrinet/labextension/static/vendors-node_modules_graphlib_index_js.56cfad5b559bbb1ddb13.js
ipypetrinet/labextension/static/vendors-node_modules_graphlib_index_js.56cfad5b559bbb1ddb13.js.map
ipypetrinet/labextension/static/vendors-node_modules_lodash__baseClone_js-node_modules_lodash__baseFindIndex_js-node_modules_-cdf19a.f3f8494afddae5de6376.js
ipypetrinet/labextension/static/vendors-node_modules_lodash__baseClone_js-node_modules_lodash__baseFindIndex_js-node_modules_-cdf19a.f3f8494afddae5de6376.js.map
ipypetrinet/nbextension/extension.js
ipypetrinet/nbextension/index.js
ipypetrinet/nbextension/index.js.LICENSE.txt
ipypetrinet/nbextension/index.js.map
ipypetrinet/tests/__init__.py
ipypetrinet/tests/conftest.py
ipypetrinet/tests/test_example.py
ipypetrinet/tests/test_nbextension_path.py
ipypetrinet-1.2.0.data/data/etc/jupyter/nbconfig/notebook.d/ipypetrinet.json
ipypetrinet-1.2.0.dist-info/LICENSE.txt
ipypetrinet-1.2.0.dist-info/METADATA
ipypetrinet-1.2.0.dist-info/WHEEL
ipypetrinet-1.2.0.dist-info/top_level.txt
ipypetrinet-1.2.0.dist-info/RECORD
